mullvad_async/__init__.py
mullvad_async/const.py
mullvad_async-0.1.0.dist-info/LICENSE.txt
mullvad_async-0.1.0.dist-info/METADATA
mullvad_async-0.1.0.dist-info/WHEEL
mullvad_async-0.1.0.dist-info/top_level.txt
mullvad_async-0.1.0.dist-info/RECORD
