Metadata-Version: 2.1
Name: mullvad-async
Version: 0.1.0
Summary: Pull from Mullvad API asynchronously
Author-email: Easton Potokar <contagon6@gmail.com>
Maintainer-email: Easton Potokar <contagon6@gmail.com>
License: MIT License
Project-URL: Homepage, https://github.com/contagon/mullvad-async
Project-URL: Bug Reports, https://github.com/contagon/mullvad-async/issues
Project-URL: Source, https://github.com/contagon/mullvad-async/
Keywords: api,mullvad,async
Classifier: Development Status :: 4 - Beta
Classifier: Intended Audience :: Developers
Classifier: Topic :: Software Development :: Build Tools
Classifier: License :: OSI Approved :: MIT License
Classifier: Programming Language :: Python :: 3
Classifier: Programming Language :: Python :: 3.7
Classifier: Programming Language :: Python :: 3.8
Classifier: Programming Language :: Python :: 3.9
Classifier: Programming Language :: Python :: 3.10
Classifier: Programming Language :: Python :: 3.11
Classifier: Programming Language :: Python :: 3 :: Only
Requires-Python: >=3.7
License-File: LICENSE.txt
Requires-Dist: aiohttp
Provides-Extra: dev
Requires-Dist: check-manifest ; extra == 'dev'
Requires-Dist: pre-commit ; extra == 'dev'
Provides-Extra: test
Requires-Dist: pytest ; extra == 'test'
